{"Mazda 6": {"fullTitle": "Mazda 6", "brand": {"titleRus": "Мазда", "country": {"code": "JP", "id": 8, "title": "Япония"}, "isOutbound": false, "alias": "mazda", "logo": "http://tradeins.space/uploads/brand/30/b983c4614d3a3f291364ede80acfa14b5950730c.png", "id": 30, "title": "Mazda", "absentee": false}, "photo": "https://207231.selcdn.ru/locator-media/models_desktop_q90/tradeins.space-uploads-photo-859724-93f1c5c69568d8b20fb050d5964e60eee386cedb.png", "renderPhotos": {"render_widget_left": {"sedan": {"path": "https://tradeins.space/uploads/photo/43109/6.png", "width": 1000, "height": 500}}, "side": {"sedan": {"path": "https://tradeins.space/uploads/photo/4083233/изображение.png", "width": 900, "height": 422}}, "main_left": {"sedan": {"path": "https://tradeins.space/uploads/photo/4083250/изображение.png", "width": 900, "height": 422}}, "back": {"sedan": {"path": "https://tradeins.space/uploads/photo/4083269/изображение.png", "width": 900, "height": 422}}, "render_banner": {"sedan": {"path": "https://tradeins.space/uploads/photo/5517/mazda6-1_1.jpg", "width": 1800, "height": 540}}, "main": {"sedan": {"path": "https://tradeins.space/uploads/photo/4083228/изображение.png", "width": 900, "height": 422}}, "render_widget_right": {"sedan": {"path": "https://tradeins.space/uploads/photo/859724/93f1c5c69568d8b20fb050d5964e60eee386cedb.png", "width": 450, "height": 253}}, "front": {"sedan": {"path": "https://tradeins.space/uploads/photo/4083232/изображение.png", "width": 900, "height": 422}}, "render_side": {"sedan": {"path": "https://tradeins.space/uploads/photo/859738/3.png", "width": 135, "height": 76}}}, "title": "6", "colorsCount": 1, "count": 1, "transportType": "Легковые", "minprice": 2733100}, "Cadillac ESCALADE": {"fullTitle": "Cadillac ESCALADE", "brand": {"titleRus": "Кадиллак", "country": {"code": "US", "id": 1, "title": "США"}, "isOutbound": false, "alias": "cadillac", "logo": "http://tradeins.space/uploads/brand/6/0ec447411c90475a1fa9557d1ad64879347f7036.png", "id": 6, "title": "Cadillac", "absentee": false}, "photo": "https://tradeins.space/uploads/photo/147093/escalade.jpg", "renderPhotos": {"main": {"offroad": {"path": "https://tradeins.space/uploads/photo/56923/escalade.jpg", "width": 640, "height": 430}}, "render_side": {"offroad": {"path": "https://tradeins.space/uploads/photo/20157/cadillac_esc_200x123.png", "width": 200, "height": 123}}, "render_widget_right": {"offroad": {"path": "https://tradeins.space/uploads/photo/147093/escalade.jpg", "width": 960, "height": 540}}, "front": {"offroad": {"path": "https://tradeins.space/uploads/photo/56972/silver-coast.jpg", "width": 960, "height": 540}}, "side": {"offroad": {"path": "https://tradeins.space/uploads/photo/56973/black-raven.jpg", "width": 960, "height": 540}}, "back": {"offroad": {"path": "https://tradeins.space/uploads/photo/56952/radiant-silver.jpg", "width": 960, "height": 540}}, "main_left": {"offroad": {"path": "https://tradeins.space/uploads/photo/6871171/6.png", "width": 960, "height": 540}}}, "title": "ESCALADE", "colorsCount": 3, "count": 14, "transportType": "Легковые", "minprice": 2733100}, "Jaguar F-PACE": {"fullTitle": "Jaguar F-PACE", "brand": {"titleRus": "Ягуар", "country": {"code": "GB", "id": 9, "title": "Великобритания"}, "isOutbound": true, "alias": "jaguar", "logo": "http://tradeins.space/uploads/brand/24/bd45c1b176803cb2eb64fe5d1dd6ac5f331b92a8.png", "id": 24, "title": "Jaguar", "absentee": false}, "photo": "https://207231.selcdn.ru/locator-media/models_desktop_q90/tradeins.space-uploads-photo-83480-f-pace-widget-right_1.png", "renderPhotos": {"render_widget_left": {"crossover": {"path": "https://tradeins.space/uploads/photo/82856/f-pace_1.png", "width": 971, "height": 548}}, "side": {"crossover": {"path": "https://tradeins.space/uploads/photo/872690/Без названия (20).png", "width": 1280, "height": 560}}, "main_left": {"crossover": {"path": "https://tradeins.space/uploads/photo/872691/Без названия (21).png", "width": 1280, "height": 560}}, "back": {"crossover": {"path": "https://tradeins.space/uploads/photo/7164979/Screenshot_2020-09-11 Я выбрал свой идеальный JAGUAR F-PACE Взгляните (2).jpg", "width": 1673, "height": 828}}, "main": {"crossover": {"path": "https://tradeins.space/uploads/photo/872671/Без названия (5).png", "width": 1280, "height": 560}}, "side_right": {"crossover": {"path": "https://tradeins.space/uploads/photo/378585/20ac621495c7ace7f0209877538797b9.png", "width": 1280, "height": 560}}, "render_widget_right": {"crossover": {"path": "https://tradeins.space/uploads/photo/83480/f-pace-widget-right_1.png", "width": 450, "height": 300}}, "front": {"crossover": {"path": "https://tradeins.space/uploads/photo/158235/1AB.png", "width": 1280, "height": 560}}, "render_side": {"crossover": {"path": "https://tradeins.space/uploads/photo/36015/fpace.png", "width": 460, "height": 160}}}, "title": "F-PACE", "colorsCount": 13, "count": 17, "transportType": "Легковые", "minprice": 2733100}, "BMW 3": {"fullTitle": "BMW 3 серии", "brand": {"titleRus": "БМВ", "country": {"code": "DE", "id": 2, "title": "Германия"}, "isOutbound": false, "alias": "bmw", "logo": "http://tradeins.space/uploads/brand/4/35dad01f02c529a28f45cb8d47d089fa1e911639.png", "id": 4, "title": "BMW", "absentee": false}, "photo": "https://207231.selcdn.ru/locator-media/models_desktop_q90/tradeins.space-uploads-photo-5393800-dadc828c82c5af24c412839d4b7c9919fcd6ecb3.png", "renderPhotos": {"side": {"sedan": {"path": "https://tradeins.space/uploads/photo/3291875/11_0001_Слой 3.jpg", "width": 942, "height": 459}}, "main_left": {"sedan": {"path": "https://tradeins.space/uploads/photo/3291877/11_0000_Слой 4.jpg", "width": 942, "height": 459}}, "back": {"sedan": {"path": "https://tradeins.space/uploads/photo/3291876/11_0001_Слой 5.jpg", "width": 942, "height": 459}}, "main": {"sedan": {"path": "https://tradeins.space/uploads/photo/3291873/11_0002_Слой 1.jpg", "width": 942, "height": 459}}, "render_widget_right": {"sedan": {"path": "https://tradeins.space/uploads/photo/5393800/dadc828c82c5af24c412839d4b7c9919fcd6ecb3.png", "width": 450, "height": 300}}, "front": {"sedan": {"path": "https://tradeins.space/uploads/photo/3291874/11_0003_Слой 3.jpg", "width": 942, "height": 459}}}, "title": "3 серии", "colorsCount": 5, "count": 11, "transportType": "Легковые", "minprice": 2733100}, "BMW 5": {"fullTitle": "BMW 5 серия", "brand": {"titleRus": "БМВ", "country": {"code": "DE", "id": 2, "title": "Германия"}, "isOutbound": false, "alias": "bmw", "logo": "http://tradeins.space/uploads/brand/4/35dad01f02c529a28f45cb8d47d089fa1e911639.png", "id": 4, "title": "BMW", "absentee": false}, "photo": "https://207231.selcdn.ru/locator-media/models_desktop_q90/tradeins.space-uploads-photo-7049209-ef6bba94a8c5ebc8f5c0a30a35e0d6e2e2bd773b.png", "renderPhotos": {"render_widget_left": {"sedan": {"path": "https://tradeins.space/uploads/photo/7049208/d6fb97e5c5e6ddc93814f15d0a1e1b5c7610cce5.png", "width": 450, "height": 300}}, "side": {"sedan": {"path": "https://tradeins.space/uploads/photo/7064356/image.png", "width": 1349, "height": 632}}, "render_main": {"sedan": {"path": "https://tradeins.space/uploads/photo/7049185/c9b2cbe0e202ba76b02dbbc73a31716a1dc65005.png", "width": 450, "height": 300}}, "back": {"sedan": {"path": "https://tradeins.space/uploads/photo/7064352/image.png", "width": 1349, "height": 632}}, "main": {"sedan": {"path": "https://tradeins.space/uploads/photo/7064355/image.png", "width": 1349, "height": 632}}, "render_widget_right": {"sedan": {"path": "https://tradeins.space/uploads/photo/7049209/ef6bba94a8c5ebc8f5c0a30a35e0d6e2e2bd773b.png", "width": 450, "height": 300}}, "front": {"sedan": {"path": "https://tradeins.space/uploads/photo/7064350/image.png", "width": 1349, "height": 632}}, "render_side": {"sedan": {"path": "https://tradeins.space/uploads/photo/7049186/77ead88ef74f1ae0fd40a9b017557e0168427044.png", "width": 450, "height": 300}}, "back_left": {"sedan": {"path": "https://tradeins.space/uploads/photo/7064353/image.png", "width": 1349, "height": 632}}}, "title": "5 серия", "colorsCount": 2, "count": 2, "transportType": "Легковые", "minprice": 2733100}, "KIA Sportage": {"fullTitle": "KIA Sportage", "brand": {"titleRus": "Киа", "country": {"code": "KR", "id": 5, "title": "Южная Корея"}, "isOutbound": false, "alias": "kia", "logo": "http://tradeins.space/uploads/brand/26/75bb737582b2872e4604976820b0d1cd8112fb9c.png", "id": 26, "title": "KIA", "absentee": false}, "photo": "https://207231.selcdn.ru/locator-media/models_desktop_q90/tradeins.space-uploads-photo-690002-spt3.png", "renderPhotos": {"render_widget_left": {"crossover": {"path": "https://tradeins.space/uploads/photo/689991/ad4ff01a386c2d057ad0983ad052ddd336506464.png", "width": 506, "height": 417}}, "side": {"crossover": {"path": "https://tradeins.space/uploads/photo/689853/d275c67875adbd453b1adc7b48c2a808.jpg", "width": 600, "height": 370}}, "render_main": {"crossover": {"path": "https://tradeins.space/uploads/photo/689977/spt1.png", "width": 450, "height": 300}}, "main_left": {"crossover": {"path": "https://tradeins.space/uploads/photo/2510214/kcsgt.jpg", "width": 600, "height": 370}}, "back": {"crossover": {"path": "https://tradeins.space/uploads/photo/689931/0e2c06b811bf3dcf3102a51c5b25f4d3.jpg", "width": 600, "height": 370}}, "main": {"crossover": {"path": "https://tradeins.space/uploads/photo/696027/11dade5da87bd3c7a66b7e5e63c9e865.jpg", "width": 600, "height": 370}}, "render_widget_right": {"crossover": {"path": "https://tradeins.space/uploads/photo/690002/spt3.png", "width": 450, "height": 300}}, "front": {"crossover": {"path": "https://tradeins.space/uploads/photo/696028/c009cd8b1cd5b25272b37730dec335e3.jpg", "width": 600, "height": 370}}, "render_side": {"crossover": {"path": "https://tradeins.space/uploads/photo/31742/sportage-new.png", "width": 127, "height": 70}}}, "title": "Sportage", "colorsCount": 8, "count": 37, "transportType": "Легковые", "minprice": 2733100}, "KIA Optima": {"fullTitle": "KIA Optima", "brand": {"titleRus": "Киа", "country": {"code": "KR", "id": 5, "title": "Южная Корея"}, "isOutbound": false, "alias": "kia", "logo": "http://tradeins.space/uploads/brand/26/75bb737582b2872e4604976820b0d1cd8112fb9c.png", "id": 26, "title": "KIA", "absentee": false}, "photo": "https://207231.selcdn.ru/locator-media/models_desktop_q90/tradeins.space-uploads-photo-203148-18.png", "renderPhotos": {"render_widget_left": {"sedan": {"path": "https://tradeins.space/uploads/photo/52359/8d904bfd7855a171d9bc66089031e7e1a643e0ba.png", "width": 506, "height": 417}}, "side": {"sedan": {"path": "https://tradeins.space/uploads/photo/2298655/14f081033ed8cd7188daad876966169b.jpg", "width": 600, "height": 370}}, "render_main": {"sedan": {"path": "https://tradeins.space/uploads/photo/102715/65.png", "width": 450, "height": 300}}, "main_left": {"sedan": {"path": "https://tradeins.space/uploads/photo/2510814/t.jpg", "width": 600, "height": 370}}, "back": {"sedan": {"path": "https://tradeins.space/uploads/photo/2510813/b.jpg", "width": 600, "height": 370}}, "main": {"sedan": {"path": "https://tradeins.space/uploads/photo/2510796/m.jpg", "width": 600, "height": 370}}, "render_widget_right": {"sedan": {"path": "https://tradeins.space/uploads/photo/203148/18.png", "width": 450, "height": 301}}, "front": {"sedan": {"path": "https://tradeins.space/uploads/photo/2510797/f.jpg", "width": 600, "height": 370}}, "render_side": {"sedan": {"path": "https://tradeins.space/uploads/photo/29915/new_optima.png", "width": 128, "height": 69}}}, "title": "Optima", "colorsCount": 3, "count": 3, "transportType": "Легковые", "minprice": 2733100}, "KIA K5": {"fullTitle": "KIA K5", "brand": {"titleRus": "Киа", "country": {"code": "KR", "id": 5, "title": "Южная Корея"}, "isOutbound": false, "alias": "kia", "logo": "http://tradeins.space/uploads/brand/26/75bb737582b2872e4604976820b0d1cd8112fb9c.png", "id": 26, "title": "KIA", "absentee": false}, "photo": "https://207231.selcdn.ru/locator-media/models_desktop_q90/tradeins.space-uploads-photo-7045549-1ed1ce8ed1655930df51584bf5e294dbdee4f469.png", "renderPhotos": {"render_widget_left": {"sedan": {"path": "https://tradeins.space/uploads/photo/7045548/27f05a2d5eb6359d01ffee9a7c4598ff36aec530.png", "width": 450, "height": 300}}, "side": {"sedan": {"path": "https://tradeins.space/uploads/photo/7045552/загруженное (3).png", "width": 1000, "height": 500}}, "render_widget_side": {"sedan": {"path": "https://tradeins.space/uploads/photo/7045546/0b0aa9c5a448269db8548b12062b0d4f8dc74db6.png", "width": 450, "height": 300}}, "render_main": {"sedan": {"path": "https://tradeins.space/uploads/photo/7045547/242272bd4c48bf8e22fc2ba811fbd84cc8732a4e.png", "width": 450, "height": 300}}, "main_left": {"sedan": {"path": "https://tradeins.space/uploads/photo/7045554/загруженное.png", "width": 1000, "height": 500}}, "back": {"sedan": {"path": "https://tradeins.space/uploads/photo/7045553/загруженное (4).png", "width": 1000, "height": 500}}, "main": {"sedan": {"path": "https://tradeins.space/uploads/photo/7045556/загруженное (2).png", "width": 1000, "height": 500}}, "render_widget_right": {"sedan": {"path": "https://tradeins.space/uploads/photo/7045549/1ed1ce8ed1655930df51584bf5e294dbdee4f469.png", "width": 450, "height": 301}}, "front": {"sedan": {"path": "https://tradeins.space/uploads/photo/7045555/загруженное (1).png", "width": 1000, "height": 500}}}, "title": "K5", "colorsCount": 6, "count": 13, "transportType": "Легковые", "minprice": 2733100}, "Land Rover RANGE ROVER VELAR": {"fullTitle": "Land Rover RANGE ROVER VELAR", "brand": {"titleRus": "Ленд Ровер", "country": {"code": "GB", "id": 9, "title": "Великобритания"}, "isOutbound": false, "alias": "land-rover", "logo": "http://tradeins.space/uploads/brand/27/a75f0419f50514f5c10a0d5fd3a8710582bf0d51.png", "id": 27, "title": "Land Rover", "absentee": false}, "photo": "https://207231.selcdn.ru/locator-media/models_desktop_q90/tradeins.space-uploads-photo-96915-velar_1_1.png", "renderPhotos": {"render_widget_left": {"offroad": {"path": "https://tradeins.space/uploads/photo/96919/bezymyannyj.png", "width": 1451, "height": 727}}, "side": {"offroad": {"path": "https://tradeins.space/uploads/photo/955789/1BN.png", "width": 1036, "height": 691}}, "render_main": {"offroad": {"path": "https://tradeins.space/uploads/photo/96917/bezymyannyj.png", "width": 1451, "height": 727}}, "back": {"offroad": {"path": "https://tradeins.space/uploads/photo/174331/1AC.png", "width": 1036, "height": 691}}, "main": {"offroad": {"path": "https://tradeins.space/uploads/photo/162221/velar.png", "width": 1036, "height": 691}}, "render_widget_right": {"offroad": {"path": "https://tradeins.space/uploads/photo/96915/velar_1_1.png", "width": 450, "height": 300}}, "front": {"offroad": {"path": "https://tradeins.space/uploads/photo/2150965/1CB (1).png", "width": 1036, "height": 691}}, "render_side": {"offroad": {"path": "https://tradeins.space/uploads/photo/96913/mgslide1_l560_k18_a-fe_a-swb_gl.jpg", "width": 280, "height": 158}}}, "title": "RANGE ROVER VELAR", "colorsCount": 2, "count": 2, "transportType": "Легковые", "minprice": 2733100}, "Chevrolet Tahoe": {"fullTitle": "Chevrolet Tahoe", "brand": {"titleRus": "Шевроле", "country": {"code": "US", "id": 1, "title": "США"}, "isOutbound": false, "alias": "chevrolet", "logo": "http://tradeins.space/uploads/brand/8/1e9c0831553781563292cb6d94a43c5a2d93ecf5.png", "id": 8, "title": "Chevrolet", "absentee": false}, "photo": "https://207231.selcdn.ru/locator-media/models_desktop_q90/tradeins.space-uploads-photo-148909-d18cab06a1a529e1d1221d67bdfa8c7bb2b282fc.png", "renderPhotos": {"side": {"offroad": {"path": "https://tradeins.space/uploads/photo/60599/544e0d1a277ca.jpeg", "width": 533, "height": 400}}, "main": {"offroad": {"path": "https://tradeins.space/uploads/photo/61063/GAN.jpg", "width": 640, "height": 430}}, "render_widget_right": {"offroad": {"path": "https://tradeins.space/uploads/photo/148909/d18cab06a1a529e1d1221d67bdfa8c7bb2b282fc.png", "width": 960, "height": 540}}, "render_side": {"offroad": {"path": "https://tradeins.space/uploads/photo/44561/cars-tahoe-2-160x55.jpg", "width": 160, "height": 55}}}, "title": "Tahoe", "colorsCount": 2, "count": 2, "transportType": "Легковые", "minprice": 2733100}}